MANIFEST.in
README.rst
setup.py
json_patch/__init__.py
json_patch/patch.py
json_patch/test.py
json_patch.egg-info/PKG-INFO
json_patch.egg-info/SOURCES.txt
json_patch.egg-info/dependency_links.txt
json_patch.egg-info/requires.txt
json_patch.egg-info/top_level.txt