Metadata-Version: 1.0
Name: json-patch
Version: 0.1
Summary: Implementation of the json-patch spec
Home-page: UNKNOWN
Author: Ernst Odolphi
Author-email: ernst.odolphi@gmail.com
License: UNKNOWN
Platform: UNKNOWN
